[
    {
        "id": "MS01118",
        "name": "Lý Anh Hiển",
        "gender": "Nam",
        "dob": "2012-02-02",
        "parent_account": "phhs_MS01118",
        "parent_password": "phhs_MS01118_1234",
        "class": "6A1",
        "scores": {
            "Toán": {
                "semester_1": {
                    "oral_scores": [],
                    "quiz_15min": [],
                    "test_1period": [],
                    "midterm": null,
                    "final": null,
                    "average": null
                },
                "semester_2": {
                    "oral_scores": [],
                    "quiz_15min": [],
                    "test_1period": [],
                    "midterm": null,
                    "final": null,
                    "average": null
                }
            },
            "Văn": {
                "semester_1": {
                    "oral_scores": [],
                    "quiz_15min": [],
                    "test_1period": [],
                    "midterm": null,
                    "final": null,
                    "average": null
                },
                "semester_2": {
                    "oral_scores": [],
                    "quiz_15min": [],
                    "test_1period": [],
                    "midterm": null,
                    "final": null,
                    "average": null
                }
            },
            "KHTN": {
                "semester_1": {
                    "oral_scores": [],
                    "quiz_15min": [],
                    "test_1period": [],
                    "midterm": null,
                    "final": null,
                    "average": null
                },
                "semester_2": {
                    "oral_scores": [],
                    "quiz_15min": [],
                    "test_1period": [],
                    "midterm": null,
                    "final": null,
                    "average": null
                }
            },
            "Anh": {
                "semester_1": {
                    "oral_scores": [],
                    "quiz_15min": [],
                    "test_1period": [],
                    "midterm": null,
                    "final": null,
                    "average": null
                },
                "semester_2": {
                    "oral_scores": [],
                    "quiz_15min": [],
                    "test_1period": [],
                    "midterm": null,
                    "final": null,
                    "average": null
                }
            }
        },
        "comment": {
            "Văn": "ngu"
        }
    },
    {
        "id": "MS36844",
        "name": "Nguyễn Dương Thanh Trúc",
        "gender": "Nữ",
        "dob": "2011-03-03",
        "parent_account": "phhs_MS36844",
        "parent_password": "phhs_MS36844_1234",
        "class": "6A1",
        "scores": {
            "Toán": {
                "semester_1": {
                    "oral_scores": [],
                    "quiz_15min": [],
                    "test_1period": [],
                    "midterm": null,
                    "final": null,
                    "average": null
                },
                "semester_2": {
                    "oral_scores": [],
                    "quiz_15min": [],
                    "test_1period": [],
                    "midterm": null,
                    "final": null,
                    "average": null
                }
            },
            "Văn": {
                "semester_1": {
                    "oral_scores": [],
                    "quiz_15min": [],
                    "test_1period": [],
                    "midterm": null,
                    "final": null,
                    "average": null
                },
                "semester_2": {
                    "oral_scores": [],
                    "quiz_15min": [],
                    "test_1period": [],
                    "midterm": null,
                    "final": null,
                    "average": null
                }
            },
            "KHTN": {
                "semester_1": {
                    "oral_scores": [],
                    "quiz_15min": [],
                    "test_1period": [],
                    "midterm": null,
                    "final": null,
                    "average": null
                },
                "semester_2": {
                    "oral_scores": [],
                    "quiz_15min": [],
                    "test_1period": [],
                    "midterm": null,
                    "final": null,
                    "average": null
                }
            },
            "Anh": {
                "semester_1": {
                    "oral_scores": [],
                    "quiz_15min": [],
                    "test_1period": [],
                    "midterm": null,
                    "final": null,
                    "average": null
                },
                "semester_2": {
                    "oral_scores": [],
                    "quiz_15min": [],
                    "test_1period": [],
                    "midterm": null,
                    "final": null,
                    "average": null
                }
            }
        },
        "comment": {
            "Văn": "Em học tốt, chăm chỉ và có thái độ học tập nghiêm túc. Cô/Thầy rất hài lòng với sự cố gắng của em 💯"
        }
    },
    {
        "id": "MS83708",
        "name": "Nguyễn Văn G",
        "gender": "Nữ",
        "dob": "2012-04-04",
        "parent_account": "phhs_MS83708",
        "parent_password": "phhs_MS83708_1234",
        "class": "6A1",
        "scores": {
            "Toán": {
                "semester_1": {
                    "oral_scores": [],
                    "quiz_15min": [],
                    "test_1period": [],
                    "midterm": null,
                    "final": null,
                    "average": null
                },
                "semester_2": {
                    "oral_scores": [],
                    "quiz_15min": [],
                    "test_1period": [],
                    "midterm": null,
                    "final": null,
                    "average": null
                }
            },
            "Văn": {
                "semester_1": {
                    "oral_scores": [],
                    "quiz_15min": [],
                    "test_1period": [],
                    "midterm": null,
                    "final": null,
                    "average": null
                },
                "semester_2": {
                    "oral_scores": [],
                    "quiz_15min": [],
                    "test_1period": [],
                    "midterm": null,
                    "final": null,
                    "average": null
                }
            },
            "KHTN": {
                "semester_1": {
                    "oral_scores": [],
                    "quiz_15min": [],
                    "test_1period": [],
                    "midterm": null,
                    "final": null,
                    "average": null
                },
                "semester_2": {
                    "oral_scores": [],
                    "quiz_15min": [],
                    "test_1period": [],
                    "midterm": null,
                    "final": null,
                    "average": null
                }
            },
            "Anh": {
                "semester_1": {
                    "oral_scores": [],
                    "quiz_15min": [],
                    "test_1period": [],
                    "midterm": null,
                    "final": null,
                    "average": null
                },
                "semester_2": {
                    "oral_scores": [],
                    "quiz_15min": [],
                    "test_1period": [],
                    "midterm": null,
                    "final": null,
                    "average": null
                }
            }
        },
        "comment": {}
    },
    {
        "id": "MS25039",
        "name": "Lý Suni",
        "gender": "Nữ",
        "dob": "2012-05-05",
        "parent_account": "phhs_MS25039",
        "parent_password": "phhs_MS25039_1234",
        "class": "6A1",
        "scores": {
            "Toán": {
                "semester_1": {
                    "oral_scores": [],
                    "quiz_15min": [],
                    "test_1period": [],
                    "midterm": null,
                    "final": null,
                    "average": null
                },
                "semester_2": {
                    "oral_scores": [],
                    "quiz_15min": [],
                    "test_1period": [],
                    "midterm": null,
                    "final": null,
                    "average": null
                }
            },
            "Văn": {
                "semester_1": {
                    "oral_scores": [],
                    "quiz_15min": [],
                    "test_1period": [],
                    "midterm": null,
                    "final": null,
                    "average": null
                },
                "semester_2": {
                    "oral_scores": [],
                    "quiz_15min": [],
                    "test_1period": [],
                    "midterm": null,
                    "final": null,
                    "average": null
                }
            },
            "KHTN": {
                "semester_1": {
                    "oral_scores": [],
                    "quiz_15min": [],
                    "test_1period": [],
                    "midterm": null,
                    "final": null,
                    "average": null
                },
                "semester_2": {
                    "oral_scores": [],
                    "quiz_15min": [],
                    "test_1period": [],
                    "midterm": null,
                    "final": null,
                    "average": null
                }
            },
            "Anh": {
                "semester_1": {
                    "oral_scores": [],
                    "quiz_15min": [],
                    "test_1period": [],
                    "midterm": null,
                    "final": null,
                    "average": null
                },
                "semester_2": {
                    "oral_scores": [],
                    "quiz_15min": [],
                    "test_1period": [],
                    "midterm": null,
                    "final": null,
                    "average": null
                }
            }
        },
        "comment": {}
    },
    {
        "id": "MS05711",
        "name": "Lý Money",
        "gender": "Nữ",
        "dob": "2012-06-06",
        "parent_account": "phhs_MS05711",
        "parent_password": "phhs_MS05711_1234",
        "class": "6A1",
        "scores": {
            "Toán": {
                "semester_1": {
                    "oral_scores": [],
                    "quiz_15min": [],
                    "test_1period": [],
                    "midterm": null,
                    "final": null,
                    "average": null
                },
                "semester_2": {
                    "oral_scores": [],
                    "quiz_15min": [],
                    "test_1period": [],
                    "midterm": null,
                    "final": null,
                    "average": null
                }
            },
            "Văn": {
                "semester_1": {
                    "oral_scores": [],
                    "quiz_15min": [],
                    "test_1period": [],
                    "midterm": null,
                    "final": null,
                    "average": null
                },
                "semester_2": {
                    "oral_scores": [],
                    "quiz_15min": [],
                    "test_1period": [],
                    "midterm": null,
                    "final": null,
                    "average": null
                }
            },
            "KHTN": {
                "semester_1": {
                    "oral_scores": [],
                    "quiz_15min": [],
                    "test_1period": [],
                    "midterm": null,
                    "final": null,
                    "average": null
                },
                "semester_2": {
                    "oral_scores": [],
                    "quiz_15min": [],
                    "test_1period": [],
                    "midterm": null,
                    "final": null,
                    "average": null
                }
            },
            "Anh": {
                "semester_1": {
                    "oral_scores": [],
                    "quiz_15min": [],
                    "test_1period": [],
                    "midterm": null,
                    "final": null,
                    "average": null
                },
                "semester_2": {
                    "oral_scores": [],
                    "quiz_15min": [],
                    "test_1period": [],
                    "midterm": null,
                    "final": null,
                    "average": null
                }
            }
        },
        "comment": {}
    },
    {
        "id": "MS97069",
        "name": "Nguyễn Văn B",
        "gender": "Nam",
        "dob": "1/1/2000",
        "parent_account": "phhs_MS97069",
        "parent_password": "phhs_MS97069_1234",
        "class": "6A1",
        "scores": {
            "Toán": {
                "semester_1": {
                    "oral_scores": [],
                    "quiz_15min": [],
                    "test_1period": [],
                    "midterm": null,
                    "final": null,
                    "average": null
                },
                "semester_2": {
                    "oral_scores": [],
                    "quiz_15min": [],
                    "test_1period": [],
                    "midterm": null,
                    "final": null,
                    "average": null
                }
            },
            "Văn": {
                "semester_1": {
                    "oral_scores": [],
                    "quiz_15min": [],
                    "test_1period": [],
                    "midterm": null,
                    "final": null,
                    "average": null
                },
                "semester_2": {
                    "oral_scores": [],
                    "quiz_15min": [],
                    "test_1period": [],
                    "midterm": null,
                    "final": null,
                    "average": null
                }
            },
            "KHTN": {
                "semester_1": {
                    "oral_scores": [],
                    "quiz_15min": [],
                    "test_1period": [],
                    "midterm": null,
                    "final": null,
                    "average": null
                },
                "semester_2": {
                    "oral_scores": [],
                    "quiz_15min": [],
                    "test_1period": [],
                    "midterm": null,
                    "final": null,
                    "average": null
                }
            },
            "Anh": {
                "semester_1": {
                    "oral_scores": [],
                    "quiz_15min": [],
                    "test_1period": [],
                    "midterm": null,
                    "final": null,
                    "average": null
                },
                "semester_2": {
                    "oral_scores": [],
                    "quiz_15min": [],
                    "test_1period": [],
                    "midterm": null,
                    "final": null,
                    "average": null
                }
            }
        },
        "comment": {}
    }
]