[
    {
        "id": "MS45892",
        "name": "",
        "gender": "Nam",
        "dob": "1/1/2000",
        "parent_account": "phhs_MS45892",
        "parent_password": "phhs_MS45892_1234",
        "class": "8.23",
        "scores": {},
        "comment": {}
    },
    {
        "id": "MS82736",
        "name": "dưq",
        "gender": "Nam",
        "dob": "1/1/2000",
        "parent_account": "phhs_MS82736",
        "parent_password": "phhs_MS82736_1234",
        "class": "8.23",
        "scores": {},
        "comment": {}
    }
]